Sound_cls/__init__.py
Sound_cls-1.4.2.dist-info/METADATA
Sound_cls-1.4.2.dist-info/WHEEL
Sound_cls-1.4.2.dist-info/top_level.txt
Sound_cls-1.4.2.dist-info/RECORD
