Metadata-Version: 2.1
Name: Sound-cls
Version: 1.4.2
Home-page: https://gitee.com/yuanyunqaing
Author: YuanYunQiang
Author-email: 649756903@qq.com
License: MIT Licence
Keywords: pip,SICA,featureextraction
Platform: any
Requires-Dist: torch
Requires-Dist: torchaudio
Requires-Dist: ffmpeg
Requires-Dist: resampy
Requires-Dist: soundfile
Requires-Dist: librosa
Requires-Dist: termcolor
Requires-Dist: pyaudio
